ozholiday/__init__.py
ozholiday/ozholiday.py
ozholiday-0.1.1.dist-info/DESCRIPTION.rst
ozholiday-0.1.1.dist-info/METADATA
ozholiday-0.1.1.dist-info/RECORD
ozholiday-0.1.1.dist-info/WHEEL
ozholiday-0.1.1.dist-info/metadata.json
ozholiday-0.1.1.dist-info/top_level.txt
