Metadata-Version: 2.0
Name: ozholiday
Version: 0.1.1
Summary: A simple function to check if a given date a public holiday in Australia
Home-page: https://github.com/zhongdai/ozholiday
Author: Zhong Dai
Author-email: zhongdai.au@gmail.com
License: BSD license
Keywords: ozholiday
Platform: UNKNOWN
Classifier: Development Status :: 2 - Pre-Alpha
Classifier: Intended Audience :: Developers
Classifier: License :: OSI Approved :: BSD License
Classifier: Natural Language :: English
Classifier: Programming Language :: Python :: 2
Classifier: Programming Language :: Python :: 2.7
Classifier: Programming Language :: Python :: 3
Classifier: Programming Language :: Python :: 3.4
Classifier: Programming Language :: Python :: 3.5
Classifier: Programming Language :: Python :: 3.6
